odoo/addons/geoengine_base_geolocalize/README.rst
odoo/addons/geoengine_base_geolocalize/__init__.py
odoo/addons/geoengine_base_geolocalize/__manifest__.py
odoo/addons/geoengine_base_geolocalize/i18n/geoengine_base_geolocalize.pot
odoo/addons/geoengine_base_geolocalize/models/__init__.py
odoo/addons/geoengine_base_geolocalize/models/res_partner.py
odoo/addons/geoengine_base_geolocalize/static/description/icon.png
odoo/addons/geoengine_base_geolocalize/tests/__init__.py
odoo/addons/geoengine_base_geolocalize/tests/test_geoengine_partner.py
odoo/addons/geoengine_base_geolocalize/views/res_partner_view.xml
odoo11_addon_geoengine_base_geolocalize-11.0.0.1.0.99.dev2.dist-info/METADATA
odoo11_addon_geoengine_base_geolocalize-11.0.0.1.0.99.dev2.dist-info/WHEEL
odoo11_addon_geoengine_base_geolocalize-11.0.0.1.0.99.dev2.dist-info/top_level.txt
odoo11_addon_geoengine_base_geolocalize-11.0.0.1.0.99.dev2.dist-info/RECORD
