Metadata-Version: 2.1
Name: odoo11-addon-geoengine-base-geolocalize
Version: 11.0.0.1.0.99.dev2
Summary: Geospatial support for base_geolocalize
Home-page: http://www.acsone.eu
Author: ACSONE SA/NV, Odoo Community Association (OCA)
Author-email: support@odoo-community.org
License: AGPL-3
Platform: UNKNOWN
Classifier: Programming Language :: Python
Classifier: Framework :: Odoo
Classifier: License :: OSI Approved :: GNU Affero General Public License v3
Requires-Python: >=2.7, !=3.0.*, !=3.1.*, !=3.2.*, !=3.3.*, !=3.4.*
Requires-Dist: odoo11-addon-geoengine-partner
Requires-Dist: odoo (<11.1dev,>=11.0a)
Requires-Dist: requests
